Workbook

Sheet 越南备货清单
A1: 品牌 | B1: 判断热销 | C1: 链接 | D1: 产品图片 | E1: SKU | F1: 名称 | G1: 成本 | H1: 陆运 | J1: 库存 | K1: 30天 | L1: 15天 | M1: 7天 | N1: 30天日销 | O1: 15天日销 | P1: 7天日销 | Q1: 增量趋势 | R1: 调节系数 | S1: 日均 | T1: 调节后日均 | U1: 综合判定-是否清货 | V1: 去波段预处理 | W1: 款号 | X1: 款内最大日销 | Y1: 款内SKU数 | Z1: 款内动销SKU数 | AA1: 上架时间 | AB1: 可售天数 | AC1: 备货天数 | AD1: 传过的店铺 | AE1: 跨境价 | AF1: 闪购价 | AG1: 毛利润 | AH1: 毛利率 | AI1: 前台价 | AJ1: 折扣价 | AK1: 闪购价 | AL1: 毛利润 | AM1: 毛利率 | AN1: 总在途 | AO1: 9/18陆运 | AV1: 30天 | AW1: 15天 | AX1: 7天 | AY1: 汇率
H2: =IF(U2="无动销无库存",0,IF(LEFT(U2,2)="清货",MIN(0,ROUNDUP(T2*AC2-J2-AN2,-1)),ROUNDUP(T2*AC2-J2-AN2,-1))) | J2: =_xlfn.IFNA(VLOOKUP(E2,雅仓库存!B:J,9,0),0) | K2: =_xlfn.IFNA(VLOOKUP(E2,雅仓动销!A:G,7,0),0) | L2: =_xlfn.IFNA(VLOOKUP(E2,雅仓动销!A:G,6,0),0) | M2: =_xlfn.IFNA(VLOOKUP(E2,雅仓动销!A:G,5,0),0) | N2: =K2/(30+AV2) | O2: =L2/(15+AW2) | P2: =M2/(7+AX2) | Q2: =IF(AND(P2=0,O2=0,N2=0),"无动销",IF(AND(P2>=O2*1.1,O2>=N2*1.1),"持续上升",IF(AND(P2<=O2*0.9,O2<=N2*0.9),"持续下滑",IF(P2>=O2*1.1,"近期回升",IF(P2<=O2*0.9,"近期回落","平稳"))))) | R2: =IF(Q2="持续上升",1.2,IF(Q2="近期回升",1.1,IF(Q2="平稳",1,IF(Q2="近期回落",0.9,IF(Q2="持续下滑",0.8,""))))) | S2: =K2*数据更改!$E$2/(30+AV2)+L2*数据更改!$F$2/(15+AW2)+M2*数据更改!$G$2/(7+AX2) | T2: =ROUNDUP(IF(R2="",0,S2*R2),2) | U2: =IF(AND(S2=0,J2=0),"无动销无库存",IF(X2<0.5,"清货-自身/整款弱销",IF(AND(S2=0,J2>0),"清货-无动销有库存",IF(AND(S2<=0.2,NOT(AND(AA2<>"未收录",IFERROR(DATEVALUE(LEFT(AA2,10))>=EDATE(TODAY(),-2),FALSE)))),"清货-自身/整款弱销",IF(AND(S2<=0.2,AA2<>"未收录",IFERROR(DATEVALUE(LEFT(AA2,10))>=EDATE(TODAY(),-2),FALSE)),"新品观察-继续备货","正常备货"))))) | V2: =IF(OR(ISNUMBER(SEARCH("&",E2)),ISNUMBER(SEARCH("+",E2)),ISNUMBER(SEARCH("x2",E2))),E2,IFERROR(IF(LEN(E2)-FIND("‖",SUBSTITUTE(E2,"-","‖",LEN(E2)-LEN(SUBSTITUTE(E2,"-",""))))<=3,LEFT(E2,FIND("‖",SUBSTITUTE(E2,"-","‖",LEN(E2)-LEN(SUBSTITUTE(E2,"-",""))))-1),E2),E2)) | W2: =IF(AND(MAX(IFERROR(FIND("‖",SUBSTITUTE(V2,"S","‖",LEN(V2)-LEN(SUBSTITUTE(V2,"S","")))),0),IFERROR(FIND("‖",SUBSTITUTE(V2,"L","‖",LEN(V2)-LEN(SUBSTITUTE(V2,"L","")))),0))>0,LEN(V2)-MAX(IFERROR(FIND("‖",SUBSTITUTE(V2,"S","‖",LEN(V2)-LEN(SUBSTITUTE(V2,"S","")))),0),IFERROR(FIND("‖",SUBSTITUTE(V2,"L","‖",LEN(V2)-LEN(SUBSTITUTE(V2,"L","")))),0))<=5),LEFT(V2,MAX(IFERROR(FIND("‖",SUBSTITUTE(V2,"S","‖",LEN(V2)-LEN(SUBSTITUTE(V2,"S","")))),0),IFERROR(FIND("‖",SUBSTITUTE(V2,"L","‖",LEN(V2)-LEN(SUBSTITUTE(V2,"L","")))),0))-1),IF(ISNUMBER(RIGHT(V2,2)*1),IF(ISNUMBER(MID(V2,LEN(V2)-2,1)*1),LEFT(V2,LEN(V2)-2),IF(ISNUMBER(MID(V2,LEN(V2)-3,1)*1),LEFT(V2,LEN(V2)-3),LEFT(V2,LEN(V2)-4))),V2)) | X2: =IFERROR(_xlfn.MAXIFS($S:$S,$W:$W,W2),0) | Y2: =COUNTIF($W:$W,W2)-COUNTIFS($W:$W,W2,$J:$J,0,$S:$S,0) | Z2: =COUNTIFS($W:$W,W2,$S:$S,">0.2") | AA2: =IFERROR(VLOOKUP(E2,库存商品信息!B:K,10,0),"未收录") | AB2: =_xlfn.IFNA(ROUNDDOWN(J2/S2,0),0) | AC2: {=IFERROR(_xlfn.IFS(B2=1,IF(S2>1,IF(AB2<15,80,70),IF(AB2<15,60,50)),B2=2,IF(S2>1,IF(AB2<15,70,60),IF(AB2<15,50,40)),TRUE,0),0)} | AF2: =ROUNDUP(AE2*0.99,-1) | AG2: =AE2/AY2*0.61-G2*1.05-5700/AY2 | AH2: =AG2/(AE2/AY2) | AI2: =AE2*1.1 | AK2: =ROUNDUP(AJ2*0.99,-1) | AL2: =AJ2/AY2*0.6-G2*1.05-1.7-3000/AY2 | AM2: =AL2/(AJ2/AY2) | AV2: =数据更改!A2 | AW2: =数据更改!B2 | AX2: =数据更改!C2 | AY2: =数据更改!D2

Sheet 雅仓库存
A1: 条码 | B1: SKU | C1: 映射条码 | D1: 仓库 | E1: 规格 | F1: 库存数量 | G1: 占用数量 | H1: 在途数量 | I1: 冻结库存 | J1: 可用库存 | K1: 中文标题 | L1: 英文标题 | M1: 图片链接

Sheet 雅仓动销
A1: SKU | B1: 商品名 | C1: 仓库 | D1: 3天销量 | E1: 7天销量 | F1: 15天销量 | G1: 30天销量 | H1: 60天销量 | I1: 90天销量 | J1: 库存 | K1: 占用 | L1: 在途 | M1: 冻结 | N1: 可用 | O1: 缺货数量 | P1: 创建日期

Sheet 数据更改
A1: 30天 | B1: 15天 | C1: 7天 | D1: 汇率 | E1: 30天销量权重 | F1: 15天销量权重 | G1: 7天销量权重
A2: 0.8 | B2: 0.8 | C2: 0 | D2: 3900 | E2: 0.1 | F2: 0.3 | G2: 0.6

Sheet 库存商品信息
A1: 条码 | B1: SKU | C1: 规格 | D1: 中文标题 | E1: 英文标题 | F1: 长 | G1: 宽 | H1: 高 | I1: 重量 | J1: 图片链接 | K1: 创建时间
